[
  {
    "lang": "en_US",
    "translations": {
      "success": "Success",
      "welcome": "Welcome",
      "summary_for_acc": "Summary for Account No.",
      "more_history": "More History",
      "session_time": "Remaining Session",
      "drawer_history": "History",
      "drawer_send_trans": "Send Transfer",
      "drawer_cards": "Your Cards",
      "drawer_profile": "Profile",
      "drawer_pass": "Change Password",
      "drawer_logout": "Logout",
      "drawer_login": "Log In",
      "drawer_register": "Register",
      "drawer_google": "Log In with Google",
      "from": "From",
      "to": "To",
      "quick_transfer": "Quick Transfer",
      "recipient_address": "Recipient's Address",
      "recipient_accn": "Recipient's Account Number",
      "trans_title": "Transfer Title",
      "amount": "Amount",
      "send_transfer": "Send Transfer",
      "send_transfer2": "Confirm? Click Again",
      "invalid_form": "Invalid Form Submission",
      "credit_card": "Credit Card",
      "reveal_data": "Reveal Data",
      "hide_data": "Hide Data",
      "pesel": "PESEL Number",
      "idnumber": "ID Number",
      "sensitivedata_profile": "Sensitive Data - Profile",
      "your_email": "Your Email",
      "firstname": "First Name",
      "lastname": "Last Name",
      "email_address": "Email Address",
      "confirm_email": "Confirm Email Address",
      "password": "Password",
      "confirm_password": "Confirm Password",
      "street_number": "Street and Number",
      "zip_code": "ZIP Code",
      "city": "City",
      "initial_acc_balance": "Initial Account Balance",
      "copied_accn": "Copied Account Number to Clipboard",
      "new_pass": "New Password",
      "password_min8ch": "Password must be at least 8 characters",
      "field_cannotempty": "Field cannot be empty",
      "confirm_new_pass": "Confirm New Password",
      "passwords_need_equal": "Passwords must match",
      "password_ch_suc": "Password changed successfully!",
      "password_ch_fail": "Failed to change password. Contact the bank for assistance.",
      "from_acc_no": "from account no.",
      "recipient_name_surname": "Recipient's First Name and Last Name",
      "invalid_textbox": "Invalid input in textbox",
      "succ_trans": "Transfer sent successfully.",
      "oauth_err": "OAuth2 login failed. Verify if you have an account with the bank.",
      "login_pass": "Enter appropriate password characters:",
      "invalidcred_err": "Invalid login credentials. Try again. After several unsuccessful attempts, the account may be locked.",
      "email_mismatch": "Email addresses must match",
      "pass_mismatch": "Passwords must match",
      "invalid_chars_pass": "Password contains forbidden characters",
      "pesel_length_err": "PESEL should have 11 digits",
      "zip_format_err": "ZIP Code should be in the format XX-XXX",
      "amount_err": "Enter the amount (with a dot) - 20.34",
      "pentest_reg_info": "Information for penetration testers - this form may not be protected (data validation). Its existence is only for the improvement of the account creation procedure.",
      "end_session_err": "Session unexpectedly ended. Log in again.",
      "insufficient_funds": "Insufficient funds in the account",
      "unexpected_err": "Unexpected error",
      "startup_err": "Failed to start the application. Contact the bank.",
      "perr_big": "Lack of uppercase letters",
      "perr_small": "Lack of lowercase letters",
      "perr_num": "Lack of digits",
      "perr_spec": "Lack of special characters",
      "registration_in": "Register in",
      "reg_succ_alert": "Registration successful. You can now log in to your account at Grzesbank24.",
      "dark_mode" : "Dark mode",
      "light_mode" : "Light mode"
    }
  },
  {
    "lang": "pl_PL",
    "translations": {
      "success": "Sukces",
      "welcome": "Witaj",
      "summary_for_acc": "Podsumowanie dla konta o nr",
      "more_history": "Więcej historii",
      "session_time": "Pozostało sesji",
      "drawer_history": "Historia",
      "drawer_send_trans": "Wyślij przelew",
      "drawer_cards": "Twoje karty",
      "drawer_profile": "Profil",
      "drawer_pass": "Zmień hasło",
      "drawer_logout": "Wyloguj się",
      "drawer_login": "Zaloguj się",
      "drawer_register": "Zarejestruj się",
      "drawer_google": "Zaloguj się z Google",
      "from": "od",
      "to": "do",
      "quick_transfer": "Przelew natychmiastowy",
      "recipient_address": "Adres odbiorcy",
      "recipient_accn": "Nr rachunku odbiorcy",
      "trans_title": "Tytuł przelewu",
      "amount": "Kwota",
      "send_transfer": "Wyślij przelew",
      "send_transfer2": "Potwierdzasz? Kliknij ponownie",
      "invalid_form": "Nieprawidłowo wypełniony formularz",
      "credit_card": "Karta kredytowa",
      "reveal_data": "Odkryj dane",
      "hide_data": "Ukryj dane",
      "pesel": "Nr pesel",
      "idnumber": "Nr dowodu osobistego",
      "sensitivedata_profile": "Dane wrażliwe - profil",
      "your_email": "Twój email",
      "firstname": "Imię",
      "lastname": "Nazwisko",
      "email_address": "Adres email",
      "confirm_email": "Potwierdź adres email",
      "password": "Hasło",
      "confirm_password": "Potwierdź hasło",
      "street_number": "Ulica i numer",
      "zip_code": "Kod pocztowy",
      "city": "Miasto",
      "initial_acc_balance": "Początkowy stan konta",
      "copied_accn": "Skopiowano nr rachunku do schowka",
      "new_pass": "Nowe hasło",
      "password_min8ch": "Hasło musi mieć min. 8 znaków",
      "field_cannotempty": "Pole nie może być puste",
      "confirm_new_pass": "Potwierdź nowe hasło",
      "passwords_need_equal": "Hasła musza być takie same",
      "password_ch_suc": "Hasło zmienione poprawnie!",
      "password_ch_fail": "Hasła nie udało się zmienić. Skontaktuj się z bankiem.",
      "from_acc_no": "z rachunku nr",
      "recipient_name_surname": "Imię i nazwisko odbiorcy",
      "invalid_textbox": "Pole wypełnione niepoprawnie",
      "succ_trans": "Przelew wysłany pomyślnie.",
      "oauth_err": "Nieudane logowanie OAuth2. Zweryfikuj czy posiadasz konto w banku.",
      "login_pass": "Podaj odpowiednie znaki hasła:",
      "invalidcred_err": "Nieprawidłowe dane logowania. Spróbuj ponownie. Po kilku nieudanych próbach, konto może zostać zablokowane.",
      "email_mismatch": "Adresy email muszą być takie same",
      "pass_mismatch": "Hasła muszą być takie same",
      "invalid_chars_pass": "Hasło zawiera znaki niedozwolone",
      "pesel_length_err": "PESEL powinien mieć 11 cyfr",
      "zip_format_err": "Kod pocztowy w formacie XX-XXX",
      "amount_err": "Podaj kwotę (z kropką) - 20.34",
      "pentest_reg_info": "Informacja dla pentesterów - ten formularz może nie być chroniony (walidacja wprowadzonych danych). Jego istnienie jest jedynie uwarunkowane usprawnieniem procedury zakładania konta.",
      "end_session_err": "Sesja niespodziewanie się zakończyła. Zaloguj się ponownie.",
      "insufficient_funds": "Niewystarczające środki na koncie",
      "unexpected_err": "Niespodziewany błąd",
      "startup_err": "Nie udało się uruchomić aplikacji. Skontaktuj się z bankiem.",
      "perr_big": "Brak dużych liter",
      "perr_small": "Brak małych liter",
      "perr_num": "Brak cyfry",
      "perr_spec": "Brak znaku specjalnego",
      "registration_in": "Zarejestruj się w",
      "reg_succ_alert": "Rejestracja udana, już możesz zalogować się na konto w Grzesbank24.",
      "dark_mode" : "Tryb ciemny",
      "light_mode" : "tryb jasny"
    }
  }
]